pysmarthashtag/__init__.py
pysmarthashtag/account.py
pysmarthashtag/cli.py
pysmarthashtag/const.py
pysmarthashtag/models.py
pysmarthashtag/api/__init__.py
pysmarthashtag/api/authentication.py
pysmarthashtag/api/client.py
pysmarthashtag/api/utils.py
pysmarthashtag/control/climate.py
pysmarthashtag/tests/__init__.py
pysmarthashtag/tests/common.py
pysmarthashtag/tests/conftest.py
pysmarthashtag/tests/test_account.py
pysmarthashtag/tests/test_actions.py
pysmarthashtag/tests/replys/Human_and_vehicle_relationship_does_not_exist.json
pysmarthashtag/tests/replys/api_access.json
pysmarthashtag/tests/replys/auth_context.url
pysmarthashtag/tests/replys/auth_intermediate.url
pysmarthashtag/tests/replys/auth_result.url
pysmarthashtag/tests/replys/climate_success.json
pysmarthashtag/tests/replys/login_result.json
pysmarthashtag/tests/replys/ota_response.json
pysmarthashtag/tests/replys/soc_80.json
pysmarthashtag/tests/replys/soc_90.json
pysmarthashtag/tests/replys/token_expired.json
pysmarthashtag/tests/replys/vehicle_info.json
pysmarthashtag/tests/replys/vehicle_info2.json
pysmarthashtag/tests/replys/vehicle_info_dc_charging.json
pysmarthashtag/tests/replys/vehicle_response.json
pysmarthashtag/tests/replys/vehicle_result.json
pysmarthashtag/vehicle/__init__.py
pysmarthashtag/vehicle/battery.py
pysmarthashtag/vehicle/climate.py
pysmarthashtag/vehicle/maintenance.py
pysmarthashtag/vehicle/position.py
pysmarthashtag/vehicle/running.py
pysmarthashtag/vehicle/safety.py
pysmarthashtag/vehicle/tires.py
pysmarthashtag/vehicle/vehicle.py
pysmarthashtag-0.7.0.dist-info/licenses/AUTHORS
pysmarthashtag-0.7.0.dist-info/licenses/LICENSE
pysmarthashtag-0.7.0.dist-info/METADATA
pysmarthashtag-0.7.0.dist-info/WHEEL
pysmarthashtag-0.7.0.dist-info/pbr.json
pysmarthashtag-0.7.0.dist-info/top_level.txt
pysmarthashtag-0.7.0.dist-info/RECORD
