Metadata-Version: 2.4
Name: pySmartHashtag
Version: 0.7.0
Summary: A python library to get information from Smart #1 and #3 web API
Home-page: https://github.com/dasBasti/pySmartHashtag
Author: dasBasti
Author-email: Bastian Neumann <neumann.bastian@gmail.com>
License: MIT License
Project-URL: Homepage, https://github.com/DasBasti/pySmartHashtag
Project-URL: Issues, https://github.com/DasBasti/pySmartHashtag/issues
Classifier: Development Status :: 3 - Alpha
Classifier: Intended Audience :: Developers
Classifier: License :: OSI Approved :: MIT License
Classifier: Programming Language :: Python :: 3.9
Classifier: Programming Language :: Python :: 3.10
Classifier: Programming Language :: Python :: 3.11
Classifier: Programming Language :: Python :: 3.12
Requires-Python: >= 3.9
License-File: LICENSE
License-File: AUTHORS
Dynamic: author
Dynamic: home-page
Dynamic: license-file
Dynamic: requires-python
